libsrgtk/GuiBase.py
libsrgtk/GuiRequest.py
libsrgtk/GuiRequestQueue.py
libsrgtk/__init__.py
libsrgtk-0.1.1.dist-info/METADATA
libsrgtk-0.1.1.dist-info/WHEEL
libsrgtk-0.1.1.dist-info/top_level.txt
libsrgtk-0.1.1.dist-info/RECORD
