Metadata-Version: 2.1
Name: libsrgtk
Version: 0.1.1
Summary: Tk GUI on top of libsrg
Home-page: https://gitlab.com/SRG_gitlab/libsrgtk
Author: Steven Goncalo
Author-email: srg_pypi@ice9mail.com
Classifier: Programming Language :: Python :: 3
Classifier: License :: OSI Approved :: MIT License
Classifier: Development Status :: 4 - Beta
Classifier: Intended Audience :: Developers
Classifier: Natural Language :: English
Classifier: Operating System :: POSIX
Requires-Python: >=3.6
